sms/__init__.py
sms/admin.py
sms/apps.py
sms/models.py
sms/serializers.py
sms/tests.py
sms/urls.py
sms/utils.py
sms/views.py
sms/migrations/0001_initial.py
sms/migrations/0002_alter_sms_partinfo.py
sms/migrations/0003_alter_sms_options_sms_created_at.py
sms/migrations/__init__.py
smsuz-0.0.1.dist-info/LICENSE
smsuz-0.0.1.dist-info/METADATA
smsuz-0.0.1.dist-info/WHEEL
smsuz-0.0.1.dist-info/top_level.txt
smsuz-0.0.1.dist-info/RECORD
