Metadata-Version: 2.1
Name: smsuz
Version: 0.0.1
Summary: This is the API SMS Gateway Sayqal.uz
Home-page: https://abexlab.uz
Author: IMOWWW
Author-email: imowww@yandex.ru
License: MIT
Project-URL: GitHub, https://github.com/IMOWWW/smsuz.git
Keywords: sms gateway,django,api,smsuz,sms,uz
Classifier: Programming Language :: Python :: 3
Classifier: Framework :: Django
Classifier: License :: OSI Approved :: MIT License
Classifier: Operating System :: OS Independent
Requires-Python: >=3.6
License-File: LICENSE
Requires-Dist: requests>=2.25.1
Requires-Dist: Django>=3.2
Requires-Dist: djangorestframework>=3.12
